split_dataset/__init__.py
split_dataset/blocks.py
split_dataset/split_dataset.py
split_dataset-0.4.4.dist-info/LICENSE
split_dataset-0.4.4.dist-info/METADATA
split_dataset-0.4.4.dist-info/WHEEL
split_dataset-0.4.4.dist-info/top_level.txt
split_dataset-0.4.4.dist-info/RECORD
