Metadata-Version: 2.1
Name: split-dataset
Version: 0.4.4
Summary: A package for HDF5-based chunked arrays
Home-page: https://github.com/portugueslab/split_dataset
Author: Vilim Stih & Luigi Petrucco @portugueslab
Author-email: luigi.petrucco@gmail.com
License: GNU General Public License v3
Keywords: split_dataset
Platform: UNKNOWN
Classifier: Development Status :: 2 - Pre-Alpha
Classifier: Intended Audience :: Developers
Classifier: License :: OSI Approved :: GNU General Public License v3 (GPLv3)
Classifier: Natural Language :: English
Classifier: Programming Language :: Python :: 3
Classifier: Programming Language :: Python :: 3.5
Classifier: Programming Language :: Python :: 3.6
Classifier: Programming Language :: Python :: 3.7
Classifier: Programming Language :: Python :: 3.8
Requires-Python: >=3.5
License-File: LICENSE
Requires-Dist: flammkuchen
Requires-Dist: numpy
Provides-Extra: dev
Requires-Dist: pip ; extra == 'dev'
Requires-Dist: bump2version ; extra == 'dev'
Requires-Dist: wheel ; extra == 'dev'
Requires-Dist: flake8 ; extra == 'dev'
Requires-Dist: coverage ; extra == 'dev'
Requires-Dist: Sphinx ; extra == 'dev'
Requires-Dist: twine ; extra == 'dev'
Requires-Dist: black ; extra == 'dev'
Requires-Dist: isort ; extra == 'dev'
Requires-Dist: pytest ; extra == 'dev'
Requires-Dist: pytest-runner ; extra == 'dev'
Requires-Dist: pytest-cov ; extra == 'dev'
